breakhis_gradcam/__init__.py
breakhis_gradcam/_nbdev.py
breakhis_gradcam/data.py
breakhis_gradcam/resnet.py
breakhis_gradcam/utils.py
breakhis_gradcam/vis.py
breakhis_gradcam-0.0.1.dist-info/LICENSE
breakhis_gradcam-0.0.1.dist-info/METADATA
breakhis_gradcam-0.0.1.dist-info/WHEEL
breakhis_gradcam-0.0.1.dist-info/entry_points.txt
breakhis_gradcam-0.0.1.dist-info/top_level.txt
breakhis_gradcam-0.0.1.dist-info/RECORD
